agentboard/__init__.py
agentboard/core_constants.py
agentboard/run_agent_board.py
agentboard/summary.py
agentboard/utils.py
agentboard/db/__init__.py
agentboard/db/db_sqllite.py
agentboard/db/schema.sql
agentboard/db/setup_db.sh
agentboard/db/sqllite_database.db
agentboard/log/__init__.py
agentboard/log/main_demo.log
agentboard/static/.DS_Store
agentboard/static/__init__.py
agentboard/static/audio/__init__.py
agentboard/static/audio/plan_input_audio_0.wav
agentboard/static/css/__init__.py
agentboard/static/css/agent_board_log.css
agentboard/static/css/chat_visualizer.css
agentboard/static/css/common.css
agentboard/static/css/workflow_styles.css
agentboard/static/css/x.css
agentboard/static/img/__init__.py
agentboard/static/img/icon_bot.png
agentboard/static/img/icon_children.jpg
agentboard/static/img/icon_female.png
agentboard/static/img/icon_female_chat.png
agentboard/static/img/icon_female_chat_2.webp
agentboard/static/img/icon_male_chat.jpg
agentboard/static/img/male_icon_1.webp
agentboard/static/img/plan_input_image_0.png
agentboard/static/img/plan_input_image_1.png
agentboard/static/img/plan_input_image_2.png
agentboard/static/img/plan_input_image_3.png
agentboard/static/img/plan_input_image_4.png
agentboard/static/img/plan_input_image_5.png
agentboard/static/img/plan_input_image_6.png
agentboard/static/img/plan_input_image_7.png
agentboard/static/img/profile.jpg
agentboard/static/js/__init__.py
agentboard/static/js/chat_visualizer.js
agentboard/static/js/common.js
agentboard/static/js/workflow_script.js
agentboard/static/video/__init__.py
agentboard/static/video/act_output_video.mp4
agentboard/static/video/demo_video.mp4
agentboard/templates/.DS_Store
agentboard/templates/__init__.py
agentboard/templates/agent_activities.html
agentboard/templates/agentboard_main.html
agentboard/templates/agentboard_workflow.html
agentboard/templates/comments.html
agentboard/templates/index.html
agentboard/templates/workflow_index.html
agentboard/templates/x_post_detail.html
agentboard-0.0.2.dist-info/METADATA
agentboard-0.0.2.dist-info/WHEEL
agentboard-0.0.2.dist-info/entry_points.txt
agentboard-0.0.2.dist-info/top_level.txt
agentboard-0.0.2.dist-info/RECORD
