Metadata-Version: 2.1
Name: agentboard
Version: 0.0.2
Summary: AI Agent Visualization Toolkit, AI Agents development, such as agent loop, chat messages, tools/functions, workflow and raw data types including text, dict or json, image, audio, video, etc. 
Author-email: aihubadmin@126.com
Project-URL: homepage, http://www.deepnlp.org/blog?category=agentboard
Project-URL: repository, https://github.com/AI-Hub-Admin/agentboard
Keywords: Agent Board Visualization,AI Agent,Visualize
Classifier: Development Status :: 3 - Alpha
Classifier: Intended Audience :: Developers
Classifier: Topic :: Software Development :: Build Tools
Classifier: License :: OSI Approved :: MIT License
Requires-Python: >=3.6
Requires-Dist: Flask>=2.0.0
Requires-Dist: torch>=2.0.0
Requires-Dist: torchaudio>=2.0.0
Requires-Dist: torchvision>=0.17.0
Requires-Dist: tensorflow>=1.13.0
Requires-Dist: pillow>=9.0.0
Requires-Dist: contextvars>=2.4
Provides-Extra: dev
Provides-Extra: test
